odyssey_posbus_client/__init__.py
odyssey_posbus_client/_pbc.cpython-310-x86_64-linux-gnu.so
odyssey_posbus_client/pbc_go.h
odyssey_posbus_client/posbus.py
odyssey_posbus_client/Makefile
odyssey_posbus_client/compat.py
odyssey_posbus_client/build.py
odyssey_posbus_client/cmath.py
odyssey_posbus_client/pbc.c
odyssey_posbus_client/pbc.go
odyssey_posbus_client/go.py
odyssey_posbus_client/_pbc.cpython-310-x86_64-linux-gnu.h
odyssey_posbus_client-0.0.1a5.dist-info/RECORD
odyssey_posbus_client-0.0.1a5.dist-info/WHEEL
odyssey_posbus_client-0.0.1a5.dist-info/METADATA
