Metadata-Version: 2.1
Name: odyssey-posbus-client
Version: 0.0.1a5
Summary: Odyssey posbus client
Project-URL: Documentation, https://github.com/momentum-xyz/posbus-client/tree/develop/py#readme
Project-URL: Issues, https://github.com/momentum-xyz/posbus-client/issues
Project-URL: Source, https://github.com/momentum-xyz/posbus-client
License-Expression: GPL-3.0-only
Classifier: Development Status :: 3 - Alpha
Classifier: Programming Language :: Python
Classifier: Programming Language :: Python :: 3.10
Classifier: Programming Language :: Python :: 3.11
Classifier: Programming Language :: Python :: Implementation :: CPython
Requires-Python: >=3.10
